skosprovider_atramhasis/__init__.py
skosprovider_atramhasis/cache_utils.py
skosprovider_atramhasis/providers.py
skosprovider_atramhasis/utils.py
skosprovider_atramhasis-1.1.0.dist-info/METADATA
skosprovider_atramhasis-1.1.0.dist-info/WHEEL
skosprovider_atramhasis-1.1.0.dist-info/licenses/LICENSE
skosprovider_atramhasis-1.1.0.dist-info/RECORD
