Metadata-Version: 2.4
Name: skosprovider_atramhasis
Version: 1.1.0
Summary: Skosprovider implementation of Atramhasis Vocabularies
Project-URL: History, https://github.com/OnroerendErfgoed/skosprovider_atramhasis/blob/master/CHANGES.rst
Project-URL: Tracker, https://github.com/OnroerendErfgoed/skosprovider_atramhasis/issues
Project-URL: Source, https://github.com/OnroerendErfgoed/skosprovider_atramhasis
Project-URL: Documentation, https://skosprovider-atramhasis.readthedocs.io/en/latest/
Author-email: Flanders Heritage Agency <ict@onroerenderfgoed.be>
License-Expression: MIT
License-File: LICENSE
Keywords: rdf,skos,skosprovider,thesauri,vocabularies
Classifier: Development Status :: 5 - Production/Stable
Classifier: Framework :: Pyramid
Classifier: Programming Language :: Python
Classifier: Programming Language :: Python :: 3.10
Classifier: Programming Language :: Python :: 3.11
Classifier: Programming Language :: Python :: 3.12
Classifier: Programming Language :: Python :: 3.13
Classifier: Topic :: Internet :: WWW/HTTP
Classifier: Topic :: Internet :: WWW/HTTP :: WSGI :: Application
Requires-Python: <3.13.11,>=3.10
Requires-Dist: dogpile-cache>=1.1.4
Requires-Dist: requests>=2.32.3
Requires-Dist: skosprovider>=1.2.0
Provides-Extra: dev
Requires-Dist: coveralls>=4.0.1; extra == 'dev'
Requires-Dist: pytest-cov>=5.0.0; extra == 'dev'
Requires-Dist: pytest>=8.3.3; extra == 'dev'
Requires-Dist: responses>=0.25.3; extra == 'dev'
Requires-Dist: uv>=0.4.1; extra == 'dev'
